pydantic_modelable/__init__.py
pydantic_modelable/loader.py
pydantic_modelable/mixins.py
pydantic_modelable/model.py
pydantic_modelable-0.1.2.dist-info/licenses/LICENSE
pydantic_modelable-0.1.2.dist-info/METADATA
pydantic_modelable-0.1.2.dist-info/WHEEL
pydantic_modelable-0.1.2.dist-info/top_level.txt
pydantic_modelable-0.1.2.dist-info/RECORD
