Metadata-Version: 2.4
Name: pydantic-modelable
Version: 0.1.2
Summary: A set of pydantic utilities, to extend models on package load
Author-email: David Pineau <dav.pineau@gmail.com>
License-Expression: BSD-3-Clause
Project-URL: Homepage, https://joacchim.github.io/pydantic-modelable/
Project-URL: Source, https://github.com/Joacchim/pydantic-modelable
Classifier: Development Status :: 3 - Alpha
Classifier: Programming Language :: Python
Classifier: Programming Language :: Python :: Implementation :: CPython
Classifier: Programming Language :: Python :: Implementation :: PyPy
Classifier: Programming Language :: Python :: 3
Classifier: Programming Language :: Python :: 3 :: Only
Classifier: Programming Language :: Python :: 3.10
Classifier: Programming Language :: Python :: 3.11
Classifier: Programming Language :: Python :: 3.12
Classifier: Programming Language :: Python :: 3.13
Classifier: Programming Language :: Python :: 3.14
Classifier: Intended Audience :: Developers
Classifier: Intended Audience :: Information Technology
Classifier: Operating System :: OS Independent
Classifier: Topic :: Software Development :: Libraries :: Python Modules
Classifier: Framework :: Pydantic :: 2
Classifier: Typing :: Typed
Requires-Python: >=3.10
License-File: LICENSE
Requires-Dist: pydantic>=2.11
Requires-Dist: aenum>=3.1.13
Provides-Extra: test
Requires-Dist: mypy==1.18.2; extra == "test"
Requires-Dist: ruff==0.13.2; extra == "test"
Requires-Dist: pytest; extra == "test"
Provides-Extra: doc
Requires-Dist: mkdocs; extra == "doc"
Requires-Dist: mkdocstrings[python]; extra == "doc"
Dynamic: license-file
